{"edges": [[0, 1], [1, 0], [2, 3], [3, 2], [3, 2], [2, 3], [3, 4], [4, 3], [5, 4], [4, 5], [6, 7], [7, 6], [8, 9], [9, 8], [8, 10], [10, 8], [8, 4], [4, 8], [11, 12], [12, 11], [11, 13], [13, 11], [11, 4], [4, 11], [14, 4], [4, 14], [15, 4], [4, 15], [16, 10], [10, 16], [16, 4], [4, 16], [17, 4], [4, 17], [18, 19], [19, 18], [18, 20], [20, 18], [18, 21], [21, 18], [18, 22], [22, 18], [18, 4], [4, 18], [23, 4], [4, 23], [12, 11], [11, 12], [12, 4], [4, 12], [19, 18], [18, 19], [19, 24], [24, 19], [25, 4], [4, 25], [26, 4], [4, 26], [27, 28], [28, 27], [28, 27], [27, 28], [28, 10], [10, 28], [28, 4], [4, 28], [29, 10], [10, 29], [29, 4], [4, 29], [30, 4], [4, 30], [31, 24], [24, 31], [20, 18], [18, 20], [32, 4], [4, 32], [9, 8], [8, 9], [33, 34], [34, 33], [33, 4], [4, 33], [1, 0], [0, 1], [1, 10], [10, 1], [35, 7], [7, 35], [21, 18], [18, 21], [21, 24], [24, 21], [36, 4], [4, 36], [22, 18], [18, 22], [22, 24], [24, 22], [24, 19], [19, 24], [24, 31], [31, 24], [24, 21], [21, 24], [24, 22], [22, 24], [24, 37], [37, 24], [24, 38], [38, 24], [7, 6], [6, 7], [7, 35], [35, 7], [7, 4], [4, 7], [10, 8], [8, 10], [10, 16], [16, 10], [10, 28], [28, 10], [10, 29], [29, 10], [10, 1], [1, 10], [39, 4], [4, 39], [40, 4], [4, 40], [13, 11], [11, 13], [37, 24], [24, 37], [34, 33], [33, 34], [34, 4], [4, 34], [4, 3], [3, 4], [4, 5], [5, 4], [4, 8], [8, 4], [4, 11], [11, 4], [4, 14], [14, 4], [4, 15], [15, 4], [4, 16], [16, 4], [4, 17], [17, 4], [4, 18], [18, 4], [4, 23], [23, 4], [4, 12], [12, 4], [4, 25], [25, 4], [4, 26], [26, 4], [4, 28], [28, 4], [4, 29], [29, 4], [4, 30], [30, 4], [4, 32], [32, 4], [4, 33], [33, 4], [4, 36], [36, 4], [4, 7], [7, 4], [4, 39], [39, 4], [4, 40], [40, 4], [4, 34], [34, 4], [38, 24], [24, 38]], "labels": {"0": "1", "1": "2", "2": "1", "3": "2", "4": "23", "5": "1", "6": "1", "7": "3", "8": "3", "9": "1", "10": "5", "11": "3", "12": "2", "13": "1", "14": "1", "15": "1", "16": "2", "17": "1", "18": "5", "19": "2", "20": "1", "21": "2", "22": "2", "23": "1", "24": "6", "25": "1", "26": "1", "27": "1", "28": "3", "29": "2", "30": "1", "31": "1", "32": "1", "33": "2", "34": "2", "35": "1", "36": "1", "37": "1", "38": "1", "39": "1", "40": "1"}, "target": 9}