{"edges": [[0, 1], [0, 2], [0, 3], [0, 4], [1, 0], [1, 5], [1, 6], [1, 7], [2, 0], [2, 7], [8, 3], [9, 5], [9, 3], [9, 10], [9, 6], [11, 12], [12, 11], [12, 5], [12, 10], [5, 1], [5, 9], [5, 12], [5, 13], [3, 0], [3, 8], [3, 9], [3, 6], [3, 4], [10, 9], [10, 12], [6, 1], [6, 9], [6, 3], [6, 7], [14, 15], [7, 1], [7, 2], [7, 6], [7, 4], [15, 14], [4, 0], [4, 3], [4, 7], [4, 13], [13, 5], [13, 4], [13, 16], [16, 13]], "labels": {"0": "4", "1": "4", "2": "2", "3": "5", "4": "4", "5": "4", "6": "4", "7": "4", "8": "1", "9": "4", "10": "2", "11": "1", "12": "3", "13": "3", "14": "1", "15": "1", "16": "1"}, "target": 3}